hebrewdate/__init__.py
hebrewdate/hebrewcalendar.py
hebrewdate/hebrewdate.py
hebrewdate/hebrewmonth.py
hebrewdate/hebrewyear.py
hebrewdate/holidays.py
hebrewdate-2.2.1.dist-info/METADATA
hebrewdate-2.2.1.dist-info/WHEEL
hebrewdate-2.2.1.dist-info/RECORD
