Metadata-Version: 2.4
Name: hebrewdate
Version: 2.2.1
Summary: A Python package for handling Hebrew dates
Project-URL: Homepage, https://github.com/Isaac-D20/hebrewdate
Project-URL: Bug Tracker, https://github.com/Isaac-D20/hebrewdate/issues
Project-URL: Changelog, https://github.com/Isaac-D20/hebrewdate/blob/main/CHANGELOG.md
Author-email: Isaac Dovolsky <yidovolsky2@gmail.com>
License-Expression: MIT
Classifier: License :: OSI Approved :: MIT License
Classifier: Operating System :: OS Independent
Classifier: Programming Language :: Python :: 3 :: Only
Classifier: Programming Language :: Python :: 3.9
Classifier: Programming Language :: Python :: 3.10
Classifier: Programming Language :: Python :: 3.11
Classifier: Programming Language :: Python :: 3.12
Classifier: Programming Language :: Python :: 3.13
Requires-Python: >=3.9
